MANIFEST.in
README.rst
setup.py
Cuckoo_processing.egg-info/PKG-INFO
Cuckoo_processing.egg-info/SOURCES.txt
Cuckoo_processing.egg-info/dependency_links.txt
Cuckoo_processing.egg-info/not-zip-safe
Cuckoo_processing.egg-info/requires.txt
Cuckoo_processing.egg-info/top_level.txt
cuckoo/processing/__init__.py
cuckoo/processing/identification/__init__.py
cuckoo/processing/post/__init__.py
cuckoo/processing/post/eventconsumer/__init__.py
cuckoo/processing/pre/__init__.py
cuckoo/processing/reporting/__init__.py
cuckoo/processing/safelist/__init__.py
cuckoo/processing/stage/__init__.py
cuckoo/processing/translate/__init__.py
cuckoo/processing/translate/threemon/__init__.py